{
  "project_info": {
    "project_number": "11200755384",
    "project_id": "projectx-1fc9d",
    "storage_bucket": "projectx-1fc9d.appspot.com"
  },
  "client": [
    {
      "client_info": {
        "mobilesdk_app_id": "1:11200755384:android:a075461c65f39df0de664d",
        "android_client_info": {
          "package_name": "kz.tohatdk.project_x"
        }
      },
      "oauth_client": [],
      "api_key": [
        {
          "current_key": "AIzaSyDop4iQWP3Ao7pKGY1A_54AYRpGAp0xREc"
        }
      ],
      "services": {
        "appinvite_service": {
          "other_platform_oauth_client": []
        }
      }
    }
  ],
  "configuration_version": "1"
}